fake_dataset/__init__.py
fake_dataset/fake_dataset.py
fake_dataset/columns/__init__.py
fake_dataset/generators/__init__.py
fake_dataset-0.0.2.dist-info/LICENSE
fake_dataset-0.0.2.dist-info/METADATA
fake_dataset-0.0.2.dist-info/WHEEL
fake_dataset-0.0.2.dist-info/dependency_links.txt
fake_dataset-0.0.2.dist-info/top_level.txt
fake_dataset-0.0.2.dist-info/RECORD
