Metadata-Version: 2.1
Name: fake-dataset
Version: 0.0.2
Summary: Toolkit for generating fake datasets.
Home-page: https://github.com/matheusfsa/fake_dataset
Author: Matheus Santos
Author-email: santosalmeidamatheus@gmail.com
License: MIT license
Keywords: fake_dataset
Platform: UNKNOWN
Classifier: Development Status :: 2 - Pre-Alpha
Classifier: Intended Audience :: Developers
Classifier: License :: OSI Approved :: MIT License
Classifier: Natural Language :: English
Classifier: Programming Language :: Python :: 3
Classifier: Programming Language :: Python :: 3.7
Classifier: Programming Language :: Python :: 3.8
Classifier: Programming Language :: Python :: 3.9
Requires-Python: >=3.7
License-File: LICENSE
Requires-Dist: pandas (>=1.4.2)
Requires-Dist: numpy (>=1.22.3)
